maguro/__init__.py
maguro/maguro.py
maguro/version.py
maguro-1.1.3.dist-info/LICENSE
maguro-1.1.3.dist-info/METADATA
maguro-1.1.3.dist-info/WHEEL
maguro-1.1.3.dist-info/top_level.txt
maguro-1.1.3.dist-info/RECORD
