Metadata-Version: 2.1
Name: maguro
Version: 1.1.3
Summary: Maguro is a Python-wrapper for DSV files.
Home-page: https://github.com/rmaniego/maguro
Author: Rodney Maniego Jr.
Author-email: rod.maniego23@gmail.com
License: MIT
Download-URL: https://github.com/rmaniego/maguro/archive/v1.0.tar.gz
Keywords: CSV,TSV,DSV,File,Storage
Platform: UNKNOWN
Classifier: Development Status :: 5 - Production/Stable
Classifier: Intended Audience :: Developers
Classifier: Topic :: Software Development :: Build Tools
Classifier: License :: OSI Approved :: MIT License
Classifier: Programming Language :: Python :: 3
Requires-Python: >=3.6
License-File: LICENSE
